{
    "market_type": "futures",
    "user": "binance_01",
    "symbol": "SOLUSDT",
    "latency_simulation_ms": 1000,
    "starting_balance": 1000,
    "periodic_gain_n_days": 5,
    "start_date": "2021-01-01T00:00",
    "end_date": "2021-09-06T00:00",
    "base_dir": "backtests",
    "spot": false,
    "exchange": "binance",
    "session_name": "2021-01-01T0000_2021-09-06T0000",
    "caches_dirpath": "backtests/binance/SOLUSDT/caches/",
    "optimize_dirpath": "backtests/binance/SOLUSDT/optimize/",
    "plots_dirpath": "backtests/binance/SOLUSDT/plots/2021-09-22T150825/",
    "avg_periodic_gain_key": "avg_5days_gain",
    "maker_fee": 0.0002,
    "taker_fee": 0.0004,
    "inverse": false,
    "max_leverage": 50,
    "min_qty": 1.0,
    "min_cost": 5.0,
    "qty_step": 1.0,
    "price_step": 0.001,
    "c_mult": 1.0,
    "hedge_mode": true,
    "config_type": "scalp",
    "config_name": "scalp_longonly_binance_solusdt_53days",
    "logging_level": 0,
    "long": {
        "enabled": true,
        "markup_range": 0.008367673018866465,
        "min_markup": 0.004552776598862346,
        "n_close_orders": 10,
        "primary_ddown_factor": 2.893529695546269,
        "primary_grid_spacing": 0.0013805765658542334,
        "primary_grid_spacing_pbr_weighting": [
            0.0611118024952351,
            0.031132601214797113
        ],
        "primary_initial_qty_pct": 0.09761213319403376,
        "primary_pbr_limit": 1.285120242120011,
        "secondary_ddown_factor": 0.894844407308847,
        "secondary_grid_spacing": 0.22906341091714652,
        "secondary_pbr_limit_added": 0.3034951741625847
    },
    "shrt": {
        "enabled": false,
        "markup_range": 0.004,
        "min_markup": 0.0005,
        "n_close_orders": 10,
        "primary_ddown_factor": 0.3,
        "primary_grid_spacing": 0.001,
        "primary_grid_spacing_pbr_weighting": [
            0,
            0
        ],
        "primary_initial_qty_pct": 0.001,
        "primary_pbr_limit": 0.3,
        "secondary_ddown_factor": 0.3,
        "secondary_grid_spacing": 0.09,
        "secondary_pbr_limit_added": 0.3
    },
    "n_days": 248.0,
    "result": {
        "exchange": "binance",
        "symbol": "SOLUSDT",
        "starting_balance": 1000,
        "final_balance": 0.0,
        "final_equity": 0.0,
        "net_pnl_plus_fees": 1031.754508479993,
        "gain": 0.0,
        "n_days": 247.99998842592592,
        "average_daily_gain": 0.0,
        "average_periodic_gain": 0.15763677918298344,
        "adjusted_daily_gain": 0.0,
        "sharpe_ratio": 0.9992307032764921,
        "profit_sum": 58147.44680000001,
        "loss_sum": -53617.685000000005,
        "fee_sum": -3498.00729152,
        "lowest_eqbal_ratio": 0.03681618152242531,
        "closest_bkr": 0.05877951104669574,
        "n_fills": 19469,
        "n_entries": 2277,
        "n_closes": 17191,
        "n_reentries": 1079,
        "n_initial_entries": 1198,
        "n_normal_closes": 17191,
        "n_stop_loss_closes": 0,
        "biggest_psize": 1665.0,
        "mean_hrs_between_fills": 0.3057010643154711,
        "mean_hrs_between_fills_long": 0.3057010643154711,
        "mean_hrs_between_fills_shrt": 0.0,
        "max_hrs_no_fills_long": 2527.697222222222,
        "max_hrs_no_fills_shrt": 0.0,
        "max_hrs_no_fills_same_side": 2527.697222222222,
        "max_hrs_no_fills": 2527.697222222222
    }
}